{
  "name": "mitigation_cb_hlib2",
  "data": [
    {
      "seriesName": "INDBIO",
      "seriesValues": [
        [
          2018,
          0.0923469400533698
        ],
        [
          2019,
          0.0456184696260244
        ],
        [
          2020,
          0.0474475957011668
        ],
        [
          2021,
          0.1082549679720588
        ],
        [
          2022,
          0.1098887632765673
        ],
        [
          2023,
          0.7658416817630161
        ],
        [
          2024,
          1.0561984713376777
        ],
        [
          2025,
          1.3683274720311767
        ],
        [
          2026,
          1.7034968044586891
        ],
        [
          2027,
          1.9848382493834145
        ],
        [
          2028,
          2.2662639071463837
        ],
        [
          2029,
          2.5477737966586447
        ],
        [
          2030,
          2.829367936835011
        ],
        [
          2031,
          3.144796918499773
        ],
        [
          2032,
          3.4904286654089045
        ],
        [
          2033,
          3.841933101077098
        ],
        [
          2034,
          4.199387112996474
        ],
        [
          2035,
          4.562868489707136
        ],
        [
          2036,
          4.932455930724724
        ],
        [
          2037,
          5.296945367196033
        ],
        [
          2038,
          5.666102551902941
        ],
        [
          2039,
          6.039973704349637
        ],
        [
          2040,
          6.418605454071859
        ],
        [
          2041,
          6.8020448440583
        ],
        [
          2042,
          7.179802121244779
        ],
        [
          2043,
          7.561326228528752
        ],
        [
          2044,
          7.946646242279641
        ],
        [
          2045,
          8.335791440014301
        ],
        [
          2046,
          8.728791301705845
        ],
        [
          2047,
          9.125818437285174
        ],
        [
          2048,
          9.52677236634776
        ],
        [
          2049,
          9.931683369797275
        ],
        [
          2050,
          10.340581938215982
        ]
      ]
    },
    {
      "seriesName": "INDCOA",
      "seriesValues": [
        [
          2018,
          3.6393266670822397
        ],
        [
          2019,
          3.3139440386628958
        ],
        [
          2020,
          3.1859865789701827
        ],
        [
          2021,
          3.742185812645158
        ],
        [
          2022,
          3.7986632725145038
        ],
        [
          2023,
          3.9489217344367296
        ],
        [
          2024,
          4.105123762229234
        ],
        [
          2025,
          4.2675044572953365
        ],
        [
          2026,
          4.436308220618899
        ],
        [
          2027,
          4.436972473152054
        ],
        [
          2028,
          4.437636825144344
        ],
        [
          2029,
          4.438301276610685
        ],
        [
          2030,
          4.438965827565956
        ],
        [
          2031,
          4.439630478025049
        ],
        [
          2032,
          4.478930394407753
        ],
        [
          2033,
          4.518578196371316
        ],
        [
          2034,
          4.558576963422996
        ],
        [
          2035,
          4.598929802330038
        ],
        [
          2036,
          4.639639847361058
        ],
        [
          2037,
          4.670760486305255
        ],
        [
          2038,
          4.702089868643353
        ],
        [
          2039,
          4.733629394533172
        ],
        [
          2040,
          4.415787704108183
        ],
        [
          2041,
          3.829345217870695
        ],
        [
          2042,
          3.4216722991011927
        ],
        [
          2043,
          3.0096284471792343
        ],
        [
          2044,
          2.593179083076386
        ],
        [
          2045,
          2.1722893855723995
        ],
        [
          2046,
          1.7469242896674428
        ],
        [
          2047,
          1.3170691125775764
        ],
        [
          2048,
          0.882654061738983
        ],
        [
          2049,
          0.4436431155728
        ]
      ]
    },
    {
      "seriesName": "INDCOK",
      "seriesValues": [
        [
          2018,
          5.496980830392155
        ],
        [
          2019,
          5.3542697226315905
        ],
        [
          2020,
          5.055729064244645
        ],
        [
          2021,
          5.7406538050031255
        ],
        [
          2022,
          5.827292352934206
        ],
        [
          2023,
          5.407357931427875
        ],
        [
          2024,
          5.361185849070728
        ],
        [
          2025,
          4.991997448175038
        ],
        [
          2026,
          4.8368395976584315
        ],
        [
          2027,
          4.486205848659418
        ],
        [
          2028,
          4.1354669897904985
        ],
        [
          2029,
          3.784622997436269
        ],
        [
          2030,
          3.433673847976598
        ],
        [
          2031,
          3.1440813498265165
        ],
        [
          2032,
          2.6701031777524435
        ],
        [
          2033,
          2.2929804666400053
        ],
        [
          2034,
          1.9089718958661241
        ],
        [
          2035,
          1.5179851082252709
        ],
        [
          2036,
          1.1213008840365588
        ],
        [
          2037,
          0.7145661742947695
        ],
        [
          2038,
          0.3023246249946091
        ]
      ]
    },
    {
      "seriesName": "INDDST",
      "seriesValues": [
        [
          2018,
          1.0573140161806918
        ],
        [
          2019,
          0.4951101085666428
        ],
        [
          2020,
          0.5191927558379641
        ],
        [
          2021,
          0.5266807400825058
        ],
        [
          2022,
          0.534629460924067
        ],
        [
          2023,
          0.5106201720816332
        ],
        [
          2024,
          0.5127630307265411
        ],
        [
          2025,
          0.514276473398582
        ],
        [
          2026,
          0.515107353409298
        ],
        [
          2027,
          0.4956699172389409
        ],
        [
          2028,
          0.4762266487496162
        ],
        [
          2029,
          0.4567775466305408
        ],
        [
          2030,
          0.4373226095706859
        ],
        [
          2031,
          0.6248401289850128
        ],
        [
          2032,
          0.6303712570694827
        ],
        [
          2033,
          0.4306969608539843
        ],
        [
          2034,
          0.3592852661658992
        ],
        [
          2035,
          0.33981157895456093
        ],
        [
          2036,
          0.3199649736073908
        ],
        [
          2037,
          0.2991032164998572
        ],
        [
          2038,
          0.2779472009927887
        ],
        [
          2039,
          0.2564939181748736
        ],
        [
          2040,
          0.2347403320089837
        ],
        [
          2041,
          0.2126833791036651
        ],
        [
          2042,
          0.19004106063931842
        ],
        [
          2043,
          0.1671559787833706
        ],
        [
          2044,
          0.1440262130026253
        ],
        [
          2045,
          0.1206498293124543
        ],
        [
          2046,
          0.0970248801886128
        ],
        [
          2047,
          0.0731505501433069
        ],
        [
          2048,
          0.0490229628695128
        ],
        [
          2049,
          0.0246401177140584
        ]
      ]
    },
    {
      "seriesName": "INDELC",
      "seriesValues": [
        [
          2018,
          3.0852450267620153
        ],
        [
          2019,
          2.7851925104106483
        ],
        [
          2020,
          2.594086356338341
        ],
        [
          2021,
          2.594424522524985
        ],
        [
          2022,
          2.633579848901303
        ],
        [
          2023,
          2.736583072914189
        ],
        [
          2024,
          2.8448302993618997
        ],
        [
          2025,
          2.9573593114237986
        ],
        [
          2026,
          3.0756534852333415
        ],
        [
          2027,
          3.0761140056744556
        ],
        [
          2028,
          3.076574595069716
        ],
        [
          2029,
          3.0770352534294543
        ],
        [
          2030,
          3.077495980763995
        ],
        [
          2031,
          3.077956777083664
        ],
        [
          2032,
          3.105203063586048
        ],
        [
          2033,
          3.132690536103016
        ],
        [
          2034,
          3.1604213296298846
        ],
        [
          2035,
          3.188397598061066
        ],
        [
          2036,
          3.215247281298046
        ],
        [
          2037,
          3.2368137289210233
        ],
        [
          2038,
          3.2585248346751943
        ],
        [
          2039,
          3.2803815688627544
        ],
        [
          2040,
          3.302384908201022
        ],
        [
          2041,
          3.3245358363339563
        ],
        [
          2042,
          3.341930662492805
        ],
        [
          2043,
          3.3594165028539393
        ],
        [
          2044,
          3.376993833627059
        ],
        [
          2045,
          3.3946631335135224
        ],
        [
          2046,
          3.4124248837193627
        ],
        [
          2047,
          3.430333292951475
        ],
        [
          2048,
          3.4483356855350134
        ],
        [
          2049,
          3.4664325546921275
        ],
        [
          2050,
          3.484624396236841
        ]
      ]
    },
    {
      "seriesName": "INDGAS",
      "seriesValues": [
        [
          2018,
          1.9577940940850904
        ],
        [
          2019,
          1.419632684114958
        ],
        [
          2020,
          1.4698514179081388
        ],
        [
          2021,
          1.412487175963117
        ],
        [
          2022,
          1.4338045802263844
        ],
        [
          2023,
          1.4597798825831974
        ],
        [
          2024,
          1.4720107536745395
        ],
        [
          2025,
          1.4826080371952974
        ],
        [
          2026,
          1.4887434642009447
        ],
        [
          2027,
          1.4526598927493408
        ],
        [
          2028,
          1.4129578810434305
        ],
        [
          2029,
          1.3632685494365933
        ],
        [
          2030,
          1.1728406428542482
        ],
        [
          2031,
          1.2727800231755335
        ],
        [
          2032,
          1.2656125858957739
        ],
        [
          2033,
          1.259293242884839
        ],
        [
          2034,
          1.2511757804038832
        ],
        [
          2035,
          1.2430457915220054
        ],
        [
          2036,
          1.19433546345772
        ],
        [
          2037,
          0.8021547503886034
        ],
        [
          2038,
          0.7454171514524243
        ],
        [
          2039,
          0.687882321418829
        ],
        [
          2040,
          0.6295421180430334
        ],
        [
          2041,
          0.6765292075472443
        ],
        [
          2042,
          0.7428453867013318
        ],
        [
          2043,
          0.7897606263599342
        ],
        [
          2044,
          0.8245021404279785
        ],
        [
          2045,
          0.8793921730550132
        ],
        [
          2046,
          0.8765843330868617
        ],
        [
          2047,
          0.8888118507266908
        ],
        [
          2048,
          0.9854044200538917
        ],
        [
          2049,
          1.1565127573023657
        ],
        [
          2050,
          1.2497551157589415
        ]
      ]
    },
    {
      "seriesName": "INDKER",
      "seriesValues": [
        [
          2018,
          0.0479268929390899
        ],
        [
          2019,
          0.038925412306376195
        ],
        [
          2020,
          0.0474475957011673
        ],
        [
          2021,
          0.0413807386104793
        ],
        [
          2022,
          0.0420052610476976
        ],
        [
          2023,
          0.0401188770769242
        ],
        [
          2024,
          0.0402872391731819
        ],
        [
          2025,
          0.0404061487342261
        ],
        [
          2026,
          0.0404714300819644
        ],
        [
          2027,
          0.0389442516525851
        ],
        [
          2028,
          0.0374166149841846
        ],
        [
          2029,
          0.035888519973777
        ],
        [
          2030,
          0.0343599665183556
        ],
        [
          2031,
          0.0326468557045266
        ],
        [
          2032,
          0.031202382251014602
        ],
        [
          2033,
          0.0297297774602531
        ],
        [
          2034,
          0.0282286564788353
        ],
        [
          2035,
          0.0266986298442019
        ],
        [
          2036,
          0.0251393034332002
        ],
        [
          2037,
          0.0235002176415174
        ],
        [
          2038,
          0.0218380122842452
        ],
        [
          2039,
          0.0201524509544618
        ],
        [
          2040,
          0.0184432951139987
        ],
        [
          2041,
          0.0167103040754891
        ],
        [
          2042,
          0.014931321495337
        ],
        [
          2043,
          0.01313326525691801
        ],
        [
          2044,
          0.0113159844660074
        ],
        [
          2045,
          0.0094793271715148
        ],
        [
          2046,
          0.007623140358558
        ],
        [
          2047,
          0.0057473599551386995
        ],
        [
          2048,
          0.0038516814039883
        ],
        [
          2049,
          0.0019359475159413
        ]
      ]
    },
    {
      "seriesName": "INDLPG",
      "seriesValues": [
        [
          2018,
          0.1104656434815629
        ],
        [
          2019,
          0.09687319804754439
        ],
        [
          2020,
          0.0884095488244773
        ],
        [
          2021,
          0.0971708415585385
        ],
        [
          2022,
          0.0986373540673637
        ],
        [
          2023,
          0.1025390152694712
        ],
        [
          2024,
          0.1065950090799499
        ],
        [
          2025,
          0.1108114402200378
        ],
        [
          2026,
          0.1151946548869776
        ],
        [
          2027,
          0.1152119030892006
        ],
        [
          2028,
          0.1152291538740135
        ],
        [
          2029,
          0.1152464072418015
        ],
        [
          2030,
          0.1152636631929535
        ],
        [
          2031,
          0.1152809217278541
        ],
        [
          2032,
          0.116301396428812
        ],
        [
          2033,
          0.1173309044424778
        ],
        [
          2034,
          0.1183695257323623
        ],
        [
          2035,
          0.1194173409698159
        ],
        [
          2036,
          0.1204744315403015
        ],
        [
          2037,
          0.1212825204026524
        ],
        [
          2038,
          0.1220960295654029
        ],
        [
          2039,
          0.1229149953855168
        ],
        [
          2040,
          0.123739454463821
        ],
        [
          2041,
          0.1245694436466475
        ],
        [
          2042,
          0.1252212229997999
        ],
        [
          2043,
          0.1258764126300863
        ],
        [
          2044,
          0.1265350303809523
        ],
        [
          2045,
          0.1271970941892072
        ],
        [
          2046,
          0.1278626220855076
        ],
        [
          2047,
          0.1285336452552295
        ],
        [
          2048,
          0.1292081899552208
        ],
        [
          2049,
          0.129886274666479
        ],
        [
          2050,
          0.1305679179669862
        ]
      ]
    },
    {
      "seriesName": "INDNWS",
      "seriesValues": [
        [
          2018,
          2.2913340969782787
        ],
        [
          2019,
          2.3723365536407415
        ],
        [
          2020,
          2.2440323319387145
        ],
        [
          2021,
          2.257282344113698
        ],
        [
          2022,
          2.2913494854546452
        ],
        [
          2023,
          2.381985223531736
        ],
        [
          2024,
          2.4762061139694427
        ],
        [
          2025,
          2.57415396967427
        ],
        [
          2026,
          2.6759762130494282
        ],
        [
          2027,
          2.6763768894429045
        ],
        [
          2028,
          2.676777625830021
        ],
        [
          2029,
          2.6771784222197743
        ],
        [
          2030,
          2.6775792786211396
        ],
        [
          2031,
          2.677980195043098
        ],
        [
          2032,
          2.7016858611476717
        ],
        [
          2033,
          2.725601371449921
        ],
        [
          2034,
          2.7497285835052376
        ],
        [
          2035,
          2.7740693713121733
        ],
        [
          2036,
          2.7986256254580977
        ],
        [
          2037,
          2.8173975604563317
        ],
        [
          2038,
          2.8362954092389336
        ],
        [
          2039,
          2.8553200163795616
        ],
        [
          2040,
          2.874472232116823
        ],
        [
          2041,
          2.8937529123924066
        ],
        [
          2042,
          2.908893771548621
        ],
        [
          2043,
          2.9241138515723235
        ],
        [
          2044,
          2.939413566967449
        ],
        [
          2045,
          2.9547933344067387
        ],
        [
          2046,
          2.970253572743048
        ],
        [
          2047,
          2.985841466489847
        ],
        [
          2048,
          3.0015111655187603
        ],
        [
          2049,
          3.0172630991439777
        ],
        [
          2050,
          3.0330976989327536
        ]
      ]
    },
    {
      "seriesName": "INDRWS",
      "seriesValues": [
        [
          2018,
          1.703742596554294
        ],
        [
          2019,
          1.6914060379101676
        ],
        [
          2020,
          1.815297222581393
        ],
        [
          2021,
          1.9530230740625285
        ],
        [
          2022,
          1.9824983026619607
        ],
        [
          2023,
          2.0609172422602096
        ],
        [
          2024,
          2.1424380912419143
        ],
        [
          2025,
          2.2271835475404216
        ],
        [
          2026,
          2.3152811624812637
        ],
        [
          2027,
          2.3156278316712022
        ],
        [
          2028,
          2.3159745527682283
        ],
        [
          2029,
          2.3163213257801334
        ],
        [
          2030,
          2.3166681507146825
        ],
        [
          2031,
          2.317015027579643
        ],
        [
          2032,
          2.3375254050293126
        ],
        [
          2033,
          2.358217341760257
        ],
        [
          2034,
          2.3790924449478172
        ],
        [
          2035,
          2.400152335994132
        ],
        [
          2036,
          2.4213986506541483
        ],
        [
          2037,
          2.4376403150130392
        ],
        [
          2038,
          2.4539909212271067
        ],
        [
          2039,
          2.4704512000298506
        ],
        [
          2040,
          2.487021887056149
        ],
        [
          2041,
          2.5037037228752377
        ],
        [
          2042,
          2.516803744399052
        ],
        [
          2043,
          2.52997230860321
        ],
        [
          2044,
          2.543209774120622
        ],
        [
          2045,
          2.5565165014606763
        ],
        [
          2046,
          2.5698928530190326
        ],
        [
          2047,
          2.583379653304746
        ],
        [
          2048,
          2.596937232331968
        ],
        [
          2049,
          2.610565961547601
        ],
        [
          2050,
          2.6242662143479074
        ]
      ]
    },
    {
      "seriesName": "INDBDL",
      "seriesValues": [
        [
          2023,
          0.045156885966402896
        ],
        [
          2024,
          0.0649981306554757
        ],
        [
          2025,
          0.0863383860450153
        ],
        [
          2026,
          0.1092651961777294
        ],
        [
          2027,
          0.1287961202274396
        ],
        [
          2028,
          0.148332890594141
        ],
        [
          2029,
          0.1678755085907169
        ],
        [
          2030,
          0.1874239755302924
        ],
        [
          2033,
          0.2052543862287323
        ],
        [
          2034,
          0.2822955662732052
        ],
        [
          2035,
          0.3074485714350779
        ],
        [
          2036,
          0.3330247684485081
        ],
        [
          2037,
          0.3582664900932338
        ],
        [
          2038,
          0.3838318489900407
        ],
        [
          2039,
          0.4097240511105115
        ],
        [
          2040,
          0.4359463308738263
        ],
        [
          2041,
          0.4625019513841601
        ],
        [
          2042,
          0.4886770130725329
        ],
        [
          2043,
          0.5151133223732441
        ],
        [
          2044,
          0.5418128965336856
        ],
        [
          2045,
          0.5687777667587134
        ],
        [
          2046,
          0.5960099783014784
        ],
        [
          2047,
          0.623521355983426
        ],
        [
          2048,
          0.6513050781235283
        ],
        [
          2049,
          0.6793632455447576
        ],
        [
          2050,
          0.7076979736195514
        ]
      ]
    },
    {
      "seriesName": "INDBGS",
      "seriesValues": [
        [
          2023,
          0.0307397196038595
        ],
        [
          2024,
          0.0774672680465789
        ],
        [
          2025,
          0.1281605406039879
        ],
        [
          2026,
          0.1857400553158679
        ],
        [
          2027,
          0.2220743487336324
        ],
        [
          2028,
          0.262027119946532
        ],
        [
          2029,
          0.3119672486068133
        ],
        [
          2030,
          0.5026459897946771
        ],
        [
          2031,
          0.4029574816366063
        ],
        [
          2032,
          0.4249586633337128
        ],
        [
          2033,
          0.4462430600946283
        ],
        [
          2034,
          0.4694580480175127
        ],
        [
          2035,
          0.4928192066818476
        ],
        [
          2036,
          0.5568955318980893
        ],
        [
          2037,
          0.9608227229929422
        ],
        [
          2038,
          1.0293855901009674
        ],
        [
          2039,
          1.098825006941767
        ],
        [
          2040,
          1.169149647794207
        ],
        [
          2041,
          1.1342273820388382
        ],
        [
          2042,
          1.077385546866127
        ],
        [
          2043,
          1.039994223392254
        ],
        [
          2044,
          1.0148264570868026
        ],
        [
          2045,
          0.969560264531852
        ],
        [
          2046,
          0.9820422989774124
        ],
        [
          2047,
          0.9795688557780462
        ],
        [
          2048,
          0.892781550283814
        ],
        [
          2049,
          0.7315299349027928
        ],
        [
          2050,
          0.6481960263999773
        ]
      ]
    },
    {
      "seriesName": "INDBKE",
      "seriesValues": [
        [
          2023,
          0.003547927904751249
        ],
        [
          2024,
          0.005106833134627856
        ],
        [
          2025,
          0.006783514021073514
        ],
        [
          2026,
          0.00858484880526375
        ],
        [
          2027,
          0.010119372476654757
        ],
        [
          2028,
          0.011654355486875745
        ],
        [
          2029,
          0.013189797939079038
        ],
        [
          2030,
          0.01472569993643633
        ],
        [
          2031,
          0.0164461603925046
        ],
        [
          2032,
          0.0183252086236101
        ],
        [
          2033,
          0.020236235077986
        ],
        [
          2034,
          0.022179658661941
        ],
        [
          2035,
          0.0241559031923719
        ],
        [
          2036,
          0.0261653974508801
        ],
        [
          2037,
          0.0281486123398384
        ],
        [
          2038,
          0.0301572550591948
        ],
        [
          2039,
          0.0321915774986841
        ],
        [
          2040,
          0.0342518337831399
        ],
        [
          2041,
          0.0363382802911423
        ],
        [
          2042,
          0.038394826702295
        ],
        [
          2043,
          0.040471899057033
        ],
        [
          2044,
          0.042569655848313
        ],
        [
          2045,
          0.0446882566657125
        ],
        [
          2046,
          0.0468278622025698
        ],
        [
          2047,
          0.048989401522372
        ],
        [
          2048,
          0.0511723386529867
        ],
        [
          2049,
          0.0533768386538128
        ],
        [
          2050,
          0.0556030677273845
        ]
      ]
    },
    {
      "seriesName": "INDH2G",
      "seriesValues": [
        [
          2025,
          0.3109029836873252
        ],
        [
          2026,
          0.3934620168498939
        ],
        [
          2027,
          0.4637925249747459
        ],
        [
          2028,
          0.534144085582499
        ],
        [
          2029,
          0.6045167034008061
        ],
        [
          2030,
          0.6749103831582626
        ],
        [
          2031,
          0.6501127256388126
        ],
        [
          2032,
          0.8398835795243458
        ],
        [
          2033,
          0.9274700169850894
        ],
        [
          2034,
          1.016541284316817
        ],
        [
          2035,
          1.1071168059561884
        ],
        [
          2036,
          1.199216233882768
        ],
        [
          2037,
          1.2901112219898958
        ],
        [
          2038,
          1.3821716220523892
        ],
        [
          2039,
          1.3599296395159746
        ],
        [
          2040,
          1.3805259171601472
        ],
        [
          2041,
          1.6654612534866204
        ],
        [
          2042,
          1.7597171823949
        ],
        [
          2043,
          1.8549138592818963
        ],
        [
          2044,
          1.951058548219374
        ],
        [
          2045,
          2.0481585635396904
        ],
        [
          2046,
          2.1462212701628585
        ],
        [
          2047,
          2.2452892490593634
        ],
        [
          2048,
          2.345337935477867
        ],
        [
          2049,
          2.446374894444302
        ],
        [
          2050,
          2.5484077433769725
        ]
      ]
    }
  ]
}