{
  "name": "mitigation_cb_hlib2",
  "data": [
    {
      "seriesName": "RSDAHT",
      "seriesValues": [
        [
          2018,
          0.1187808166591111
        ],
        [
          2019,
          0.1128417758261552
        ],
        [
          2020,
          0.1069027349932
        ],
        [
          2021,
          0.10096369416024441
        ],
        [
          2022,
          0.0950246533272888
        ],
        [
          2023,
          0.8290264241656717
        ],
        [
          2024,
          0.9007302682671177
        ],
        [
          2025,
          3.649957733518883
        ],
        [
          2026,
          6.905029959101271
        ],
        [
          2027,
          10.014981366809899
        ],
        [
          2028,
          13.18964318757979
        ],
        [
          2029,
          16.39464121942833
        ],
        [
          2030,
          18.356112802852977
        ],
        [
          2031,
          18.877460432081
        ],
        [
          2032,
          18.86376488817744
        ],
        [
          2033,
          18.850080823164898
        ],
        [
          2034,
          18.836428514215886
        ],
        [
          2035,
          18.82104006570216
        ],
        [
          2036,
          18.779447525586193
        ],
        [
          2037,
          18.67023907141305
        ],
        [
          2038,
          18.560173874684796
        ],
        [
          2039,
          18.46278536344941
        ],
        [
          2040,
          18.365221346228797
        ],
        [
          2041,
          18.268407619102504
        ],
        [
          2042,
          18.17103101711578
        ],
        [
          2043,
          18.07090352711405
        ],
        [
          2044,
          17.97543433496776
        ],
        [
          2045,
          18.087322141998186
        ],
        [
          2046,
          18.221147631944675
        ],
        [
          2047,
          18.354037505608837
        ],
        [
          2048,
          18.48852711275299
        ],
        [
          2049,
          18.62195662309465
        ],
        [
          2050,
          18.66171176200753
        ]
      ]
    },
    {
      "seriesName": "RSDAHT2",
      "seriesValues": [
        [
          2018,
          0.0974250253382454
        ],
        [
          2019,
          0.0925537740713332
        ],
        [
          2020,
          0.0876825228044206
        ],
        [
          2021,
          0.0828112715375084
        ],
        [
          2022,
          0.07794002027059589
        ],
        [
          2023,
          0.2257666975686289
        ],
        [
          2024,
          0.210715584397387
        ],
        [
          2025,
          0.195664471226144
        ],
        [
          2026,
          0.1806133580549028
        ],
        [
          2027,
          0.1655622448836605
        ],
        [
          2028,
          0.1505111317124188
        ],
        [
          2029,
          0.1354600185411766
        ],
        [
          2030,
          0.1204089053699347
        ],
        [
          2031,
          0.1053577921986925
        ],
        [
          2032,
          0.0903066790274504
        ],
        [
          2033,
          0.0752555658562083
        ],
        [
          2034,
          0.0602044526849665
        ],
        [
          2035,
          0.0451533395137245
        ],
        [
          2036,
          0.0301022263424823
        ],
        [
          2037,
          0.015051113171240624
        ],
        [
          2038,
          0.1951693092296223
        ],
        [
          2039,
          0.2340863753716554
        ],
        [
          2040,
          0.257532660343968
        ],
        [
          2041,
          0.2575326603439681
        ],
        [
          2042,
          0.2575326603439681
        ],
        [
          2043,
          0.6127055269832334
        ],
        [
          2044,
          0.6965680062536426
        ],
        [
          2045,
          0.6965680062536426
        ],
        [
          2046,
          0.6965680062536426
        ],
        [
          2047,
          0.6965680062536426
        ],
        [
          2048,
          0.6965680062536426
        ],
        [
          2049,
          0.6965680062536425
        ],
        [
          2050,
          0.6965680062536426
        ]
      ]
    },
    {
      "seriesName": "RSDCOA",
      "seriesValues": [
        [
          2018,
          3.4086164450178056
        ],
        [
          2019,
          3.2381856227669203
        ],
        [
          2020,
          3.0677548005160338
        ],
        [
          2021,
          2.8973239782651374
        ],
        [
          2022,
          2.7268931560142513
        ],
        [
          2023,
          0.0657870182483223
        ],
        [
          2024,
          0.0614012170317675
        ],
        [
          2025,
          0.0570154158152126
        ],
        [
          2026,
          1.9585293842458968
        ],
        [
          2027,
          1.80625439300663
        ],
        [
          2028,
          1.5669755406143544
        ],
        [
          2029,
          0.0490479672139329
        ],
        [
          2030,
          0.0435981930790514
        ],
        [
          2031,
          0.03814841894417
        ],
        [
          2032,
          0.0326986448092886
        ],
        [
          2033,
          0.0272488706744071
        ],
        [
          2034,
          0.0217990965395257
        ],
        [
          2035,
          0.0163493224046443
        ],
        [
          2036,
          0.0108995482697628
        ],
        [
          2037,
          0.0054497741348814
        ]
      ]
    },
    {
      "seriesName": "RSDELC",
      "seriesValues": [
        [
          2018,
          2.3042074837319455
        ],
        [
          2019,
          1.431193689763233
        ],
        [
          2020,
          1.8683657903285456
        ],
        [
          2021,
          1.6393714264042216
        ],
        [
          2022,
          1.8476182325114858
        ],
        [
          2023,
          0.766963325894928
        ],
        [
          2024,
          0.774010992550103
        ],
        [
          2025,
          2.251072926964589
        ],
        [
          2026,
          4.020411106874204
        ],
        [
          2027,
          5.718857885043695
        ],
        [
          2028,
          7.496639763447179
        ],
        [
          2029,
          9.32730065182558
        ],
        [
          2030,
          10.647275255112476
        ],
        [
          2031,
          12.626543111896508
        ],
        [
          2032,
          13.680552158808714
        ],
        [
          2033,
          13.627073731635702
        ],
        [
          2034,
          13.573594206714043
        ],
        [
          2035,
          13.996163643307598
        ],
        [
          2036,
          14.393381019474548
        ],
        [
          2037,
          14.744522572704243
        ],
        [
          2038,
          14.897151010534051
        ],
        [
          2039,
          14.94274419274362
        ],
        [
          2040,
          14.89835823830976
        ],
        [
          2041,
          14.837249292834475
        ],
        [
          2042,
          14.794672507208732
        ],
        [
          2043,
          16.71661043557018
        ],
        [
          2044,
          16.959465388000655
        ],
        [
          2045,
          16.87609734759977
        ],
        [
          2046,
          16.800138406712584
        ],
        [
          2047,
          16.763682777416715
        ],
        [
          2048,
          16.722973221783153
        ],
        [
          2049,
          16.677382150462197
        ],
        [
          2050,
          16.85755074725709
        ]
      ]
    },
    {
      "seriesName": "RSDGAS",
      "seriesValues": [
        [
          2018,
          7.26164841399693
        ],
        [
          2019,
          6.41188712137909
        ],
        [
          2020,
          6.051292834898641
        ],
        [
          2021,
          5.739905838756494
        ],
        [
          2022,
          8.709486650149863
        ],
        [
          2023,
          3.58957397488612
        ],
        [
          2024,
          2.01944877502202
        ],
        [
          2025,
          1.31303062698534
        ],
        [
          2026,
          1.2400194791693768
        ],
        [
          2027,
          1.11102591514144
        ],
        [
          2028,
          1.01002355921949
        ],
        [
          2029,
          0.909021203297542
        ],
        [
          2030,
          0.808018847375593
        ],
        [
          2031,
          0.707016491453644
        ],
        [
          2032,
          0.837938454716763
        ],
        [
          2033,
          1.506920799948206
        ],
        [
          2034,
          1.452329682799387
        ],
        [
          2035,
          1.089247262099539
        ],
        [
          2036,
          0.7261648413996931
        ],
        [
          2037,
          0.36308242069984603
        ]
      ]
    },
    {
      "seriesName": "RSDHET_Det",
      "seriesValues": [
        [
          2018,
          0.16899993918420753
        ],
        [
          2019,
          0.21036372835523334
        ],
        [
          2020,
          0.06325917824387883
        ],
        [
          2023,
          0.016574700409558156
        ],
        [
          2024,
          0.03459756429530151
        ],
        [
          2025,
          0.05420244432764632
        ],
        [
          2026,
          0.07553548207633021
        ],
        [
          2027,
          0.09875622726357115
        ],
        [
          2028,
          0.12403885797886927
        ],
        [
          2029,
          0.15157351085523757
        ],
        [
          2030,
          0.18156773099701268
        ],
        [
          2031,
          0.214248052307787
        ],
        [
          2032,
          0.549861719799215
        ],
        [
          2033,
          0.5886785664736007
        ],
        [
          2034,
          0.6309930584718956
        ],
        [
          2035,
          0.6771265233713986
        ],
        [
          2036,
          0.727429577811669
        ],
        [
          2037,
          0.7822847720311126
        ],
        [
          2038,
          0.8421094704204478
        ],
        [
          2039,
          0.907358988850739
        ],
        [
          2040,
          0.9785300113255546
        ],
        [
          2041,
          1.0561643104487657
        ],
        [
          2042,
          1.1408527983045855
        ],
        [
          2043,
          1.2332399366275768
        ],
        [
          2044,
          1.3340285376118897
        ],
        [
          2045,
          1.443984989385833
        ],
        [
          2046,
          1.5507129863264189
        ],
        [
          2047,
          1.654488537017713
        ],
        [
          2048,
          1.6991155844834802
        ],
        [
          2049,
          1.6892135749630606
        ],
        [
          2050,
          1.6805081862562719
        ]
      ]
    },
    {
      "seriesName": "RSDKER",
      "seriesValues": [
        [
          2018,
          40.8217635990743
        ],
        [
          2019,
          37.170940957610284
        ],
        [
          2020,
          36.35644914479787
        ],
        [
          2021,
          35.62334607385742
        ],
        [
          2022,
          29.10429799210626
        ],
        [
          2023,
          39.74842507303616
        ],
        [
          2024,
          40.58747575076053
        ],
        [
          2025,
          39.6775382692301
        ],
        [
          2026,
          26.52758812248332
        ],
        [
          2027,
          20.86055258390433
        ],
        [
          2028,
          14.92204978512283
        ],
        [
          2029,
          9.65910535080357
        ],
        [
          2030,
          6.41169936170785
        ],
        [
          2031,
          3.67920254843981
        ],
        [
          2032,
          2.39156405391863
        ],
        [
          2033,
          1.62551333100519
        ],
        [
          2034,
          1.4947764111995
        ],
        [
          2035,
          1.17280763912029
        ],
        [
          2036,
          0.929325012314097
        ],
        [
          2037,
          0.791215027266263
        ],
        [
          2038,
          0.600040586898895
        ],
        [
          2039,
          0.0234993049520452
        ]
      ]
    },
    {
      "seriesName": "RSDLPG",
      "seriesValues": [
        [
          2018,
          1.771313487523062
        ],
        [
          2019,
          1.682747813146908
        ],
        [
          2020,
          1.8016197074279419
        ],
        [
          2021,
          1.5348630570152788
        ],
        [
          2022,
          2.278106406602615
        ],
        [
          2023,
          2.443185148723425
        ],
        [
          2024,
          2.497893805475196
        ],
        [
          2025,
          2.4629822653646345
        ],
        [
          2026,
          2.8260932732445574
        ],
        [
          2027,
          2.6198772580546392
        ],
        [
          2028,
          2.650438127315453
        ],
        [
          2029,
          2.7135101931346775
        ],
        [
          2030,
          2.7768805461162165
        ],
        [
          2031,
          2.948430550670023
        ],
        [
          2032,
          3.0413221645943738
        ],
        [
          2033,
          3.082806380953617
        ],
        [
          2034,
          3.1246009961300976
        ],
        [
          2035,
          3.166709114111992
        ],
        [
          2036,
          3.2091338699273533
        ],
        [
          2037,
          3.2600454295258032
        ],
        [
          2038,
          3.2949459922355984
        ],
        [
          2039,
          3.3278954521579545
        ],
        [
          2040,
          3.1188115535907888
        ],
        [
          2041,
          2.6847597877241536
        ],
        [
          2042,
          2.4578312136347518
        ],
        [
          2043,
          0.8926490701728109
        ],
        [
          2044,
          0.8464492012265
        ],
        [
          2045,
          0.8549136932387651
        ]
      ]
    },
    {
      "seriesName": "RSDPEA",
      "seriesValues": [
        [
          2018,
          1.6317488931261517
        ],
        [
          2019,
          1.0782154654618514
        ],
        [
          2020,
          1.021467283069123
        ],
        [
          2021,
          0.9647191006763935
        ],
        [
          2022,
          1.3053991145009227
        ],
        [
          2026,
          0.34870747130551627
        ],
        [
          2027,
          0.36158783670992584
        ],
        [
          2028,
          0.0408039098574744
        ],
        [
          2029,
          0.0367235188717269
        ],
        [
          2030,
          0.0326431278859795
        ],
        [
          2031,
          0.0285627369002321
        ],
        [
          2032,
          0.0244823459144846
        ],
        [
          2033,
          0.0204019549287372
        ],
        [
          2034,
          0.0163215639429898
        ],
        [
          2035,
          0.0122411729572423
        ],
        [
          2036,
          0.0081607819714948
        ],
        [
          2037,
          0.0040803909857474
        ]
      ]
    },
    {
      "seriesName": "RSDSOL",
      "seriesValues": [
        [
          2018,
          0.292692332835105
        ],
        [
          2019,
          0.27805771619335
        ],
        [
          2020,
          0.263423099551595
        ],
        [
          2021,
          0.24878848290984
        ],
        [
          2022,
          0.234153866268084
        ],
        [
          2023,
          0.219519249626329
        ],
        [
          2024,
          0.204884632984574
        ],
        [
          2025,
          0.190250016342818
        ],
        [
          2026,
          0.175615399701063
        ],
        [
          2027,
          0.160980783059308
        ],
        [
          2028,
          0.146346166417553
        ],
        [
          2029,
          0.131711549775797
        ],
        [
          2030,
          0.117076933134042
        ],
        [
          2031,
          0.102442316492287
        ],
        [
          2032,
          0.0878076998505316
        ],
        [
          2033,
          0.0731730832087763
        ],
        [
          2034,
          0.0585384665670211
        ],
        [
          2035,
          0.0439038499252658
        ],
        [
          2036,
          0.0292692332835105
        ],
        [
          2037,
          0.0146346166417553
        ]
      ]
    },
    {
      "seriesName": "RSDWOO",
      "seriesValues": [
        [
          2018,
          0.6425340753409117
        ],
        [
          2019,
          0.6104073715738656
        ],
        [
          2020,
          0.5782806678068197
        ],
        [
          2021,
          0.5461539640397747
        ],
        [
          2022,
          0.5140272602727288
        ],
        [
          2023,
          0.0558174267933127
        ],
        [
          2024,
          0.0520962650070918
        ],
        [
          2025,
          0.048375103220871
        ],
        [
          2026,
          0.0290589559421263
        ],
        [
          2027,
          0.0301323197258271
        ],
        [
          2028,
          0.0048294413689939
        ],
        [
          2029,
          0.014334279898639501
        ],
        [
          2030,
          0.027887853065527202
        ],
        [
          2031,
          0.028428360578565202
        ],
        [
          2032,
          0.0243671662101988
        ],
        [
          2033,
          0.020305971841832297
        ],
        [
          2034,
          0.0162447774734658
        ],
        [
          2035,
          0.0121835831050993
        ],
        [
          2036,
          0.0081223887367328
        ],
        [
          2037,
          0.0040611943683664
        ]
      ]
    },
    {
      "seriesName": "RSDETH",
      "seriesValues": [
        [
          2019,
          7.79721935317676e-05
        ],
        [
          2023,
          4.6750739919615e-05
        ],
        [
          2024,
          5.44725184742809e-05
        ],
        [
          2025,
          5.33493955743673e-05
        ],
        [
          2030,
          1.15571255050603e-05
        ],
        [
          2032,
          3.6169804165143e-06
        ],
        [
          2033,
          1.59824826532811e-05
        ],
        [
          2034,
          1.64151986382669e-05
        ],
        [
          2035,
          1.23113989787001e-05
        ],
        [
          2036,
          8.20759931913343e-06
        ],
        [
          2037,
          4.10379965956671e-06
        ]
      ]
    },
    {
      "seriesName": "RSDAHT3",
      "seriesValues": [
        [
          2023,
          0.010748227733013
        ],
        [
          2024,
          0.0120976898430591
        ],
        [
          2025,
          0.0134436910667876
        ],
        [
          2026,
          0.0148733350343689
        ],
        [
          2027,
          0.0163575692625499
        ],
        [
          2028,
          0.0179801613980555
        ],
        [
          2029,
          0.0196375180140245
        ],
        [
          2030,
          0.021312728451467998
        ],
        [
          2031,
          0.0221372473034926
        ],
        [
          2032,
          0.0234214799831102
        ],
        [
          2033,
          0.0246942337717056
        ],
        [
          2034,
          0.0259352314967826
        ],
        [
          2035,
          0.0271021624426788
        ],
        [
          2036,
          0.0282013789396301
        ],
        [
          2037,
          0.0292801010868418
        ],
        [
          2038,
          0.0303285077967137
        ],
        [
          2039,
          0.0312981251013993
        ],
        [
          2040,
          0.03218522916776229
        ],
        [
          2041,
          0.0325401637661076
        ],
        [
          2042,
          0.0328907446289246
        ],
        [
          2043,
          0.033388026265303
        ],
        [
          2044,
          0.0346674320227539
        ],
        [
          2045,
          0.0372593570905375
        ],
        [
          2046,
          0.03794715232403222
        ],
        [
          2047,
          0.0385825122085666
        ],
        [
          2048,
          0.039161452740203204
        ],
        [
          2049,
          0.039688338597965084
        ],
        [
          2050,
          0.0409493162670979
        ]
      ]
    },
    {
      "seriesName": "RSDBDL",
      "seriesValues": [
        [
          2023,
          3.6597516198097906
        ],
        [
          2024,
          4.054665569497455
        ],
        [
          2025,
          3.08801212301032
        ],
        [
          2026,
          1.85870112010301
        ],
        [
          2027,
          2.16011969268668
        ],
        [
          2028,
          2.40844163717716
        ],
        [
          2029,
          2.74079271250222
        ],
        [
          2030,
          3.089760907765083
        ],
        [
          2031,
          3.5243740450286567
        ],
        [
          2032,
          3.8409231292761716
        ],
        [
          2033,
          4.431593758417633
        ],
        [
          2034,
          4.907383625338287
        ],
        [
          2035,
          5.352761317611066
        ],
        [
          2036,
          5.820407539872225
        ],
        [
          2037,
          6.311440071748207
        ],
        [
          2038,
          6.827014951682383
        ],
        [
          2039,
          7.368365699266507
        ],
        [
          2040,
          7.936783984229821
        ],
        [
          2041,
          8.533623183441316
        ],
        [
          2042,
          9.160304342613388
        ],
        [
          2043,
          9.818319559744063
        ],
        [
          2044,
          10.509235537731264
        ],
        [
          2045,
          11.234697314617828
        ],
        [
          2046,
          11.943810080727987
        ],
        [
          2047,
          11.854781480815936
        ],
        [
          2048,
          11.806167699034274
        ],
        [
          2049,
          11.808246002349415
        ],
        [
          2050,
          11.599766559851727
        ]
      ]
    }
  ]
}