{
  "name": "mitigation_cb_hlib2",
  "data": [
    {
      "seriesName": "SRVELC",
      "seriesValues": [
        [
          2018,
          3.7411641757429344
        ],
        [
          2019,
          11.116027533732545
        ],
        [
          2020,
          9.6030320292771
        ],
        [
          2021,
          8.12577059618327
        ],
        [
          2022,
          14.950483559799391
        ],
        [
          2023,
          14.049632720027494
        ],
        [
          2024,
          16.1490291373744
        ],
        [
          2025,
          10.784620222499301
        ],
        [
          2026,
          12.514618029606936
        ],
        [
          2027,
          3.2751273337410036
        ],
        [
          2028,
          0.3535837334003146
        ],
        [
          2029,
          0.7730077631825806
        ],
        [
          2030,
          0.6124090065876678
        ],
        [
          2031,
          0.2992173190980014
        ],
        [
          2034,
          0.2700056070300576
        ],
        [
          2035,
          2.5414211022737456
        ],
        [
          2036,
          21.97023463177514
        ],
        [
          2037,
          21.992281165423623
        ],
        [
          2038,
          22.098655068567805
        ],
        [
          2039,
          22.301275461476223
        ],
        [
          2040,
          22.504507405539055
        ],
        [
          2041,
          22.708360709566588
        ],
        [
          2042,
          22.86786968733523
        ],
        [
          2043,
          23.027553419257742
        ],
        [
          2044,
          22.361211624576455
        ],
        [
          2045,
          22.281678436303032
        ],
        [
          2046,
          22.43337923916676
        ],
        [
          2047,
          22.585787629455815
        ],
        [
          2048,
          22.7327334940101
        ],
        [
          2049,
          22.40702883214011
        ],
        [
          2050,
          22.410797782572658
        ]
      ]
    },
    {
      "seriesName": "SRVGAS",
      "seriesValues": [
        [
          2018,
          3.41830396207988
        ],
        [
          2020,
          2.56196843793078
        ],
        [
          2021,
          4.72061194047688
        ],
        [
          2022,
          2.20081599208266
        ],
        [
          2023,
          4.54202367139956
        ],
        [
          2024,
          2.598736700265858
        ],
        [
          2025,
          10.21523999771914
        ],
        [
          2026,
          8.79520674681438
        ],
        [
          2027,
          21.12078837324334
        ],
        [
          2028,
          25.39409828653638
        ],
        [
          2029,
          25.39409828653638
        ],
        [
          2030,
          26.149497892068688
        ],
        [
          2031,
          27.11211819981731
        ],
        [
          2032,
          27.83485084541244
        ],
        [
          2033,
          28.177451547746163
        ],
        [
          2034,
          28.177451547746163
        ],
        [
          2035,
          25.615483109815383
        ]
      ]
    },
    {
      "seriesName": "SRVLPG",
      "seriesValues": [
        [
          2018,
          2.95271598973522
        ],
        [
          2019,
          6.0
        ],
        [
          2020,
          5.6
        ],
        [
          2021,
          6.0
        ]
      ]
    }
  ]
}