{
  "name": "mitigation_cb_hli25",
  "data": [
    {
      "seriesName": "R-SW_Att_FPL_N1",
      "seriesValues": [
        [
          2019,
          6.93024460591299
        ],
        [
          2022,
          2.39511323272431
        ],
        [
          2023,
          0.286331696383396
        ],
        [
          2039,
          3.74615148744206
        ],
        [
          2042,
          0.909322292613892
        ]
      ]
    },
    {
      "seriesName": "R-SW_Att_GAS_N1",
      "seriesValues": [
        [
          2019,
          54.5332160371814
        ],
        [
          2020,
          44.7674956170106
        ],
        [
          2021,
          31.9145830766674
        ],
        [
          2022,
          30.4675880410277
        ],
        [
          2024,
          41.4627367047033
        ],
        [
          2025,
          37.4331945468406
        ],
        [
          2027,
          3.48548554094393
        ],
        [
          2028,
          6.37734355776276
        ],
        [
          2029,
          7.59618473412355
        ]
      ]
    },
    {
      "seriesName": "R-SW_Att_HET_N1",
      "seriesValues": [
        [
          2019,
          3.32028920168849
        ],
        [
          2023,
          1.60277480495512
        ],
        [
          2024,
          6.73351130751475
        ],
        [
          2025,
          9.37749372573871
        ],
        [
          2026,
          47.7899978728409
        ],
        [
          2027,
          17.6100640753994
        ],
        [
          2033,
          4.88829114330542
        ],
        [
          2034,
          47.7757132956862
        ],
        [
          2035,
          47.2878585849201
        ],
        [
          2036,
          46.92795941486
        ],
        [
          2037,
          46.8681938136719
        ],
        [
          2038,
          47.1141511867241
        ],
        [
          2039,
          65.7245170214091
        ],
        [
          2040,
          52.5428889947818
        ],
        [
          2041,
          32.4818148838701
        ],
        [
          2042,
          36.2077397048689
        ],
        [
          2043,
          101.601970714159
        ],
        [
          2044,
          55.2098831602632
        ],
        [
          2045,
          54.6372567250006
        ],
        [
          2046,
          54.6658192109461
        ],
        [
          2047,
          54.4679935844622
        ],
        [
          2048,
          54.7851806605406
        ],
        [
          2049,
          20.0153993779603
        ],
        [
          2050,
          4.84272005181015
        ]
      ]
    },
    {
      "seriesName": "R-WH_Att_ELC_N1",
      "seriesValues": [
        [
          2019,
          7.36560888417737
        ],
        [
          2023,
          31.3272371901229
        ],
        [
          2025,
          1.07274915335203
        ],
        [
          2026,
          0.387463625482731
        ],
        [
          2027,
          27.1702857638728
        ],
        [
          2028,
          42.5266584747007
        ],
        [
          2029,
          41.4462688976179
        ],
        [
          2030,
          49.0273442591596
        ],
        [
          2031,
          46.455349293413
        ],
        [
          2032,
          47.7773248155364
        ],
        [
          2033,
          42.8926209864578
        ],
        [
          2034,
          7.24034805956674
        ],
        [
          2038,
          30.9548690155282
        ],
        [
          2040,
          0.685085527868665
        ],
        [
          2042,
          26.9980582869516
        ],
        [
          2043,
          15.2914806816356
        ],
        [
          2044,
          41.0586052721125
        ],
        [
          2045,
          47.5669314803183
        ],
        [
          2046,
          45.6804220424479
        ],
        [
          2047,
          20.2193754262072
        ]
      ]
    },
    {
      "seriesName": "R-SH_Att_GAS_N1",
      "seriesValues": [
        [
          2020,
          0.387663625483114
        ],
        [
          2021,
          0.387663625482901
        ],
        [
          2022,
          0.387663625483071
        ]
      ]
    },
    {
      "seriesName": "R-HC_Att_ELC_HPN2-AB",
      "seriesValues": [
        [
          2023,
          3.84784097100852
        ],
        [
          2043,
          0.152158175709815
        ]
      ]
    },
    {
      "seriesName": "R-HC_Att_ELC_HPN2-ABC",
      "seriesValues": [
        [
          2023,
          5.13391459754408
        ],
        [
          2043,
          0.166508802654312
        ]
      ]
    },
    {
      "seriesName": "R-HC_Att_ELC_HPN2-ABD",
      "seriesValues": [
        [
          2023,
          5.66916962495485
        ],
        [
          2043,
          0.631924398786514
        ]
      ]
    },
    {
      "seriesName": "R-HC_Att_ELC_HPN2-ABE",
      "seriesValues": [
        [
          2023,
          6.05881721431834
        ]
      ]
    },
    {
      "seriesName": "R-HC_Att_ELC_HPN2-ABF",
      "seriesValues": [
        [
          2023,
          5.19963426917619
        ],
        [
          2048,
          0.0217011137223472
        ]
      ]
    },
    {
      "seriesName": "R-HC_Att_ELC_HPN2-ABG",
      "seriesValues": [
        [
          2023,
          5.80572413860414
        ],
        [
          2049,
          0.0206712095133353
        ],
        [
          2050,
          0.0196419268902399
        ]
      ]
    },
    {
      "seriesName": "R-SW_Att_KER_N1",
      "seriesValues": [
        [
          2023,
          65.8911519608887
        ]
      ]
    },
    {
      "seriesName": "R-SH_Att_ELC_HPN2-AB",
      "seriesValues": [
        [
          2024,
          0.246528467237617
        ],
        [
          2026,
          0.130146693980394
        ],
        [
          2027,
          4.06606151318911
        ],
        [
          2028,
          4.0235183005757
        ],
        [
          2029,
          5.34486863263409
        ],
        [
          2030,
          5.11354681364377
        ],
        [
          2031,
          3.95387439887534
        ],
        [
          2032,
          4.83761991381981
        ],
        [
          2033,
          4.28962302106335
        ],
        [
          2034,
          0.262602800872202
        ],
        [
          2035,
          0.387463625483178
        ],
        [
          2036,
          0.38786362548263
        ],
        [
          2037,
          0.387263625483229
        ],
        [
          2038,
          0.0154954508881119
        ],
        [
          2042,
          0.215636148561794
        ],
        [
          2043,
          0.240847571410467
        ],
        [
          2049,
          2.82865119479656
        ],
        [
          2050,
          6.00248675218151
        ]
      ]
    },
    {
      "seriesName": "R-SH_Att_ELC_HPN2-ABD",
      "seriesValues": [
        [
          2024,
          0.0583128869160388
        ],
        [
          2025,
          0.159759052132122
        ],
        [
          2027,
          5.73096534537506
        ],
        [
          2028,
          11.4335768410231
        ],
        [
          2029,
          10.1546233525479
        ],
        [
          2030,
          14.5669775651446
        ],
        [
          2031,
          15.2373695614683
        ],
        [
          2032,
          14.1204935422332
        ],
        [
          2033,
          12.2113258766412
        ],
        [
          2043,
          0.499780854845571
        ],
        [
          2049,
          11.8110275035697
        ],
        [
          2050,
          5.70098916009589
        ]
      ]
    },
    {
      "seriesName": "R-SH_Att_ELC_HPN2-ABE",
      "seriesValues": [
        [
          2024,
          0.0264270759637759
        ],
        [
          2025,
          0.561282375010556
        ],
        [
          2026,
          0.248893130207669
        ],
        [
          2027,
          4.69989686426031
        ],
        [
          2028,
          9.61945251905899
        ],
        [
          2029,
          4.98866853024279
        ],
        [
          2030,
          7.60369370260032
        ],
        [
          2031,
          7.50647365333936
        ],
        [
          2032,
          6.94680349391513
        ],
        [
          2033,
          6.59412568089519
        ],
        [
          2043,
          1.71588223803043
        ],
        [
          2049,
          4.45202770964381
        ],
        [
          2050,
          14.3643815680865
        ]
      ]
    },
    {
      "seriesName": "R-SH_Att_ELC_HPN2-ABG",
      "seriesValues": [
        [
          2024,
          0.0563951953652706
        ],
        [
          2025,
          0.347406829956376
        ],
        [
          2026,
          0.118087885270341
        ],
        [
          2027,
          2.91558404339322
        ],
        [
          2028,
          2.57941927936086
        ],
        [
          2029,
          1.99522071207156
        ],
        [
          2030,
          2.29128435193847
        ],
        [
          2031,
          3.67838601611103
        ],
        [
          2032,
          2.5612306425484
        ],
        [
          2033,
          1.22301044315715
        ],
        [
          2043,
          0.474962626598013
        ],
        [
          2049,
          1.9699957958084
        ],
        [
          2050,
          3.29684082429545
        ]
      ]
    },
    {
      "seriesName": "R-SH_Att_ELC_HPN2-ABC",
      "seriesValues": [
        [
          2025,
          0.391964521736171
        ],
        [
          2026,
          0.0813746699695402
        ],
        [
          2027,
          6.92238368777984
        ],
        [
          2028,
          12.347121661932
        ],
        [
          2029,
          15.7112537290888
        ],
        [
          2030,
          16.9364926623058
        ],
        [
          2031,
          13.9060870294308
        ],
        [
          2032,
          17.6525241881811
        ],
        [
          2033,
          16.3266417469109
        ],
        [
          2043,
          0.59785835450052
        ],
        [
          2049,
          11.1237812861588
        ],
        [
          2050,
          13.8635956119552
        ]
      ]
    },
    {
      "seriesName": "R-SH_Att_ELC_HPN2-ABF",
      "seriesValues": [
        [
          2026,
          0.196424871537735
        ],
        [
          2027,
          3.22305793535854
        ],
        [
          2028,
          2.91123349823284
        ],
        [
          2029,
          3.63929756651551
        ],
        [
          2030,
          2.90301278900968
        ],
        [
          2031,
          2.5610222596713
        ],
        [
          2032,
          2.04631666032176
        ],
        [
          2033,
          2.63535784327354
        ],
        [
          2049,
          2.3874297640508
        ],
        [
          2050,
          6.16707204113789
        ]
      ]
    }
  ]
}