{
  "name": "mitigation_cb_hli25",
  "data": [
    {
      "serieName": "DMD_RSD-BLD-ATT",
      "seriesValues": [
        [
          2019,
          31.1768153774441
        ],
        [
          2020,
          14.6549782462246
        ],
        [
          2021,
          11.0133520803968
        ],
        [
          2022,
          11.0506403998147
        ],
        [
          2023,
          11.3074154951721
        ],
        [
          2024,
          11.3510880766031
        ],
        [
          2025,
          11.0382774903166
        ],
        [
          2026,
          11.3323015627088
        ],
        [
          2027,
          11.4206754446014
        ],
        [
          2028,
          12.0588420968487
        ],
        [
          2029,
          43.3741090735709
        ],
        [
          2030,
          26.8371625697693
        ],
        [
          2031,
          20.6235414381953
        ],
        [
          2032,
          21.9828052797365
        ],
        [
          2033,
          22.2431676893209
        ],
        [
          2034,
          22.1563806120637
        ],
        [
          2035,
          21.4809761396222
        ],
        [
          2036,
          21.4151010419535
        ],
        [
          2037,
          21.4435093226592
        ],
        [
          2038,
          21.9556651733634
        ],
        [
          2039,
          52.8171264266296
        ],
        [
          2040,
          35.796897892577
        ],
        [
          2041,
          22.3751151904349
        ],
        [
          2042,
          29.1229350371761
        ],
        [
          2043,
          30.6880394150906
        ],
        [
          2044,
          30.3543577051233
        ],
        [
          2045,
          29.419137383722
        ],
        [
          2046,
          29.0880006996132
        ],
        [
          2047,
          28.8300094719686
        ],
        [
          2048,
          29.0428868602032
        ],
        [
          2049,
          59.5679985814193
        ],
        [
          2050,
          42.2116235149066
        ]
      ]
    },
    {
      "serieName": "DMD_RSD-BLD-DET",
      "seriesValues": [
        [
          2019,
          29.353925278195
        ],
        [
          2020,
          13.2825085640914
        ],
        [
          2021,
          6.48832274063845
        ],
        [
          2022,
          7.01055719264446
        ],
        [
          2023,
          7.64145572861847
        ],
        [
          2024,
          8.00730465383637
        ],
        [
          2025,
          7.9867687892785
        ],
        [
          2026,
          8.4830798210044
        ],
        [
          2027,
          8.75508471117048
        ],
        [
          2028,
          9.49969992187845
        ],
        [
          2029,
          39.1177789995484
        ],
        [
          2030,
          23.152301523544
        ],
        [
          2031,
          11.3103662003499
        ],
        [
          2032,
          14.5604050447238
        ],
        [
          2033,
          15.123191273716
        ],
        [
          2034,
          15.3006092134988
        ],
        [
          2035,
          14.8856528393849
        ],
        [
          2036,
          14.9927062488607
        ],
        [
          2037,
          15.143342363125
        ],
        [
          2038,
          15.7084277245009
        ],
        [
          2039,
          44.8599111900637
        ],
        [
          2040,
          28.4057853373975
        ],
        [
          2041,
          13.4123103105024
        ],
        [
          2042,
          16.636566070348
        ],
        [
          2043,
          18.0681231331226
        ],
        [
          2044,
          19.6711835716993
        ],
        [
          2045,
          18.9726625919785
        ],
        [
          2046,
          18.793526509596
        ],
        [
          2047,
          18.6420707464436
        ],
        [
          2048,
          18.8964723580953
        ],
        [
          2049,
          47.7084216416802
        ],
        [
          2050,
          30.917821563478
        ]
      ]
    },
    {
      "serieName": "DMD_RSD-BLD-APT",
      "seriesValues": [
        [
          2023,
          69.3582271077104
        ],
        [
          2024,
          13.1149532266626
        ],
        [
          2025,
          12.1403966105357
        ],
        [
          2026,
          11.5151633430161
        ],
        [
          2027,
          10.9319847090942
        ],
        [
          2028,
          10.6452021665807
        ],
        [
          2029,
          10.2527988391556
        ],
        [
          2030,
          9.86196500433897
        ],
        [
          2031,
          17.6205538218298
        ],
        [
          2032,
          13.1989968511584
        ],
        [
          2033,
          82.7869442398022
        ],
        [
          2034,
          26.7203037893381
        ],
        [
          2035,
          25.8165572549452
        ],
        [
          2036,
          25.2544242316005
        ],
        [
          2037,
          24.8636681911826
        ],
        [
          2038,
          24.7381665575543
        ],
        [
          2039,
          24.3473357427751
        ],
        [
          2040,
          23.9316062394594
        ],
        [
          2041,
          21.5291115107003
        ],
        [
          2042,
          31.7265402831748
        ],
        [
          2043,
          98.8132400517727
        ],
        [
          2044,
          41.1134584635237
        ],
        [
          2045,
          40.2634877065756
        ],
        [
          2046,
          39.7455750442811
        ],
        [
          2047,
          39.380341893726
        ],
        [
          2048,
          39.2675538269497
        ],
        [
          2049,
          38.855528660445
        ],
        [
          2050,
          38.4115222135922
        ]
      ]
    }
  ]
}